README.md
setup.py
Flask_SQLAlchemy_Rest.egg-info/PKG-INFO
Flask_SQLAlchemy_Rest.egg-info/SOURCES.txt
Flask_SQLAlchemy_Rest.egg-info/dependency_links.txt
Flask_SQLAlchemy_Rest.egg-info/requires.txt
Flask_SQLAlchemy_Rest.egg-info/top_level.txt
flask_sqlalchemy_rest/__init__.py
flask_sqlalchemy_rest/model.py
flask_sqlalchemy_rest/rest.py