Metadata-Version: 1.0
Name: Flask-SQLAlchemy-Rest
Version: 0.1.8
Summary: Easily generate rest api with Flask-SQLAlchemy
Home-page: https://github.com/qf0129/flask-sqlalchemy-rest
Author: Qifei
Author-email: qf0129@qq.com
License: MIT
Platform: any
